multiset_canonical_correlation_analysis/__init__.py
multiset_canonical_correlation_analysis/helpers.py
multiset_canonical_correlation_analysis/mcca.py
multiset_canonical_correlation_analysis/plots_for_paper.py
multiset_canonical_correlation_analysis/simulations.py
multiset_canonical_correlation_analysis/visualization.py
multiset_canonical_correlation_analysis-0.0.1.dist-info/LICENSE
multiset_canonical_correlation_analysis-0.0.1.dist-info/METADATA
multiset_canonical_correlation_analysis-0.0.1.dist-info/WHEEL
multiset_canonical_correlation_analysis-0.0.1.dist-info/top_level.txt
multiset_canonical_correlation_analysis-0.0.1.dist-info/RECORD
