Metadata-Version: 2.2
Name: multiset_canonical_correlation_analysis
Version: 0.0.1
Summary: Multiset Canonical Correlation Analysis (mCCA) implementation
Home-page: https://github.com/SSTGroup/independent_vector_analysis
Author: Isabell Lehmann
Author-email: isabell.lehmann@sst.upb.de
License: LICENSE
Keywords: multiset canonical correlation analysis,multiset_canonical_correlation_analysis,bss,multiset analysis
Classifier: Programming Language :: Python :: 3
Classifier: License :: OSI Approved :: MIT License
Classifier: Operating System :: OS Independent
Requires-Python: >=3.6
License-File: LICENSE
Requires-Dist: numpy
Requires-Dist: pandas
Requires-Dist: scipy
Requires-Dist: pytest
Requires-Dist: matplotlib
Requires-Dist: independent_vector_analysis
Requires-Dist: Jinja2
Dynamic: author
Dynamic: author-email
Dynamic: classifier
Dynamic: description
Dynamic: description-content-type
Dynamic: home-page
Dynamic: keywords
Dynamic: license
Dynamic: requires-dist
Dynamic: requires-python
Dynamic: summary
